llama_index/packs/gradio_react_agent_chatbot/__init__.py
llama_index/packs/gradio_react_agent_chatbot/base.py
llama_index_packs_gradio_react_agent_chatbot-0.3.1.dist-info/METADATA
llama_index_packs_gradio_react_agent_chatbot-0.3.1.dist-info/WHEEL
llama_index_packs_gradio_react_agent_chatbot-0.3.1.dist-info/licenses/LICENSE
llama_index_packs_gradio_react_agent_chatbot-0.3.1.dist-info/RECORD
