Metadata-Version: 2.4
Name: llama-index-packs-gradio-react-agent-chatbot
Version: 0.3.1
Summary: llama-index packs gradio_react_agent_chatbot integration
Author-email: Your Name <you@example.com>
Maintainer: nerdai
License-Expression: MIT
License-File: LICENSE
Keywords: chatbot,gradio,react-agent,tools
Requires-Python: <4.0,>=3.9
Requires-Dist: llama-index-core<0.13,>=0.12.0
Requires-Dist: llama-index-llms-openai<0.5,>=0.4.0
Requires-Dist: llama-index-tools-arxiv<0.4,>=0.3.0
Requires-Dist: llama-index-tools-wikipedia<0.4,>=0.3.0
